unrealspeech/__init__.py
unrealspeech/api.py
unrealspeech/utils.py
unrealspeech-0.1.4.dist-info/METADATA
unrealspeech-0.1.4.dist-info/WHEEL
unrealspeech-0.1.4.dist-info/top_level.txt
unrealspeech-0.1.4.dist-info/RECORD
