Metadata-Version: 2.1
Name: unrealspeech
Version: 0.1.4
Summary: A Python package for interacting with the Unreal Speech API.
Home-page: https://github.com/basitng/unrealspeech
Author: Ajaga Abdulbasit
Author-email: basitng2004@gmail.com
License: MIT
Requires-Dist: requests
Requires-Dist: soundfile
Requires-Dist: sounddevice
Requires-Dist: python-dotenv
